gigsebook/__init__.py
gigsebook/fetch.py
gigsebook-1.0.3.dist-info/LICENSE
gigsebook-1.0.3.dist-info/METADATA
gigsebook-1.0.3.dist-info/WHEEL
gigsebook-1.0.3.dist-info/top_level.txt
gigsebook-1.0.3.dist-info/RECORD
