Metadata-Version: 2.1
Name: gigsebook
Version: 1.0.3
Summary: a python library to search free eBooks online using Library Genesis's database 
Home-page: https://github.com/gaurav712/GiGS-eBook
Author: Gaurav Kumar Yadav
Author-email: gaurav712@protonmail.com
License: UNKNOWN
Platform: UNKNOWN
Classifier: Programming Language :: Python :: 3
Classifier: License :: OSI Approved :: MIT License
Classifier: Operating System :: OS Independent
Requires-Python: >=3.6
Requires-Dist: bs4
Requires-Dist: urllib3
Requires-Dist: lxml
